{
  "sections": {
    "gp_section_480397238988702492": {
      "type": "gp-section-480397238988702492",
      "settings": {
      }
    },
    "gp_section_479984420086875062": {
      "type": "gp-section-479984420086875062",
      "settings": {
      }
    },
    "gp_section_479549128288764896": {
      "type": "gp-section-479549128288764896",
      "settings": {
      }
    },
    "gp_section_479984420741186486": {
      "type": "gp-section-479984420741186486",
      "settings": {
      }
    },
    "gp_section_479984420439262134": {
      "type": "gp-section-479984420439262134",
      "settings": {
      }
    },
    "gp_section_479984420774806454": {
      "type": "gp-section-479984420774806454",
      "settings": {
      }
    },
    "gp_section_479984420254647222": {
      "type": "gp-section-479984420254647222",
      "settings": {
      }
    },
    "gp_section_479984420271424438": {
      "type": "gp-section-479984420271424438",
      "settings": {
      }
    },
    "gp_section_479984420758160310": {
      "type": "gp-section-479984420758160310",
      "settings": {
      }
    },
    "gp_section_479984420439196598": {
      "type": "gp-section-479984420439196598",
      "settings": {
      }
    },
    "gp_section_479984420774937526": {
      "type": "gp-section-479984420774937526",
      "settings": {
      }
    },
    "gp_section_479984420103652278": {
      "type": "gp-section-479984420103652278",
      "settings": {
      }
    },
    "gp_section_479984420775003062": {
      "type": "gp-section-479984420775003062",
      "settings": {
      }
    },
    "gp_section_479984420757963702": {
      "type": "gp-section-479984420757963702",
      "settings": {
      }
    },
    "gp_section_479984420758029238": {
      "type": "gp-section-479984420758029238",
      "settings": {
      }
    },
    "gp_section_479984420137272246": {
      "type": "gp-section-479984420137272246",
      "settings": {
      }
    },
    "gp_section_479984420774740918": {
      "type": "gp-section-479984420774740918",
      "settings": {
      }
    },
    "gp_section_479984420019766198": {
      "type": "gp-section-479984420019766198",
      "settings": {
      }
    },
    "gp_section_479984419969500086": {
      "type": "gp-section-479984419969500086",
      "settings": {
      }
    },
    "gp_section_479984857401787318": {
      "type": "gp-section-479984857401787318",
      "settings": {
      }
    },
    "gp_section_479991586558575542": {
      "type": "gp-section-479991586558575542",
      "settings": {
      }
    },
    "gp_global_section_480397913667666716-1": {
      "type": "gp-global-section-480397913667666716",
      "settings": {
      }
    }
  },
  "order": [
    "gp_section_480397238988702492",
    "gp_section_479984420086875062",
    "gp_section_479549128288764896",
    "gp_section_479984420741186486",
    "gp_section_479984420439262134",
    "gp_section_479984420774806454",
    "gp_section_479984420254647222",
    "gp_section_479984420271424438",
    "gp_section_479984420758160310",
    "gp_section_479984420439196598",
    "gp_section_479984420774937526",
    "gp_section_479984420103652278",
    "gp_section_479984420775003062",
    "gp_section_479984420757963702",
    "gp_section_479984420758029238",
    "gp_section_479984420137272246",
    "gp_section_479984420774740918",
    "gp_section_479984420019766198",
    "gp_section_479984419969500086",
    "gp_section_479984857401787318",
    "gp_section_479991586558575542",
    "gp_global_section_480397913667666716-1"
  ]
}
